qihoo_tensornet-0.208.0.post1.dist-info/licenses/LICENSE
tensornet/__init__.py
tensornet/_opentelemetry.py
tensornet/version.py
tensornet/callbacks/__init__.py
tensornet/callbacks/callbacks.py
tensornet/core/__init__.py
tensornet/core/_pywrap_tn.cpython-37m-x86_64-linux-gnu.so
tensornet/core/_pywrap_tn.cpython-38-x86_64-linux-gnu.so
tensornet/core/_pywrap_tn.cpython-39-x86_64-linux-gnu.so
tensornet/core/gen_balance_dataset_ops.py
tensornet/core/gen_bn_table_ops.py
tensornet/core/gen_dense_table_ops.py
tensornet/core/gen_sparse_table_ops.py
tensornet/core/libtensornet.so
tensornet/data/__init__.py
tensornet/data/dataset.py
tensornet/distribute/__init__.py
tensornet/distribute/ps_strategy.py
tensornet/feature_column/__init__.py
tensornet/feature_column/category_column.py
tensornet/feature_column/sequence_category_column.py
tensornet/layers/__init__.py
tensornet/layers/embedding_features.py
tensornet/layers/normalization_layer.py
tensornet/layers/position_mapping.py
tensornet/layers/sequence_embedding_features.py
tensornet/metric/__init__.py
tensornet/metric/metrics.py
tensornet/model/Model.py
tensornet/model/__init__.py
tensornet/model/compile_utils.py
tensornet/optimizer/__init__.py
tensornet/optimizer/optimizer.py
qihoo_tensornet-0.208.0.post1.dist-info/METADATA
qihoo_tensornet-0.208.0.post1.dist-info/WHEEL
qihoo_tensornet-0.208.0.post1.dist-info/top_level.txt
qihoo_tensornet-0.208.0.post1.dist-info/RECORD
