Metadata-Version: 2.4
Name: qihoo-tensornet
Version: 0.208.0.post1
Summary: a TensorFlow-based distributed training framework optimized for large-scale sparse data
Author-email: jiangxinglei <jiangxinglei@360.cn>, gaozhiming <gaozhiming@360.cn>
License-Expression: Apache-2.0
Project-URL: homepage, https://github.com/Qihoo360/tensornet
Project-URL: issues, https://github.com/Qihoo360/tensornet/issues
Project-URL: releasenotes, https://github.com/Qihoo360/tensornet/releases
Platform: manylinux2010_x86_64
Classifier: Development Status :: 5 - Production/Stable
Classifier: Intended Audience :: Developers
Classifier: Programming Language :: Python :: 3 :: Only
Classifier: Programming Language :: Python :: 3.7
Classifier: Programming Language :: Python :: 3.8
Classifier: Programming Language :: Python :: 3.9
Requires-Python: <3.10,>=3.7
License-File: LICENSE
Requires-Dist: protobuf<3.20,>=3.9.2
Requires-Dist: tensorflow-cpu<2.9,>=2.8
Requires-Dist: tensorflow-io<0.25
Requires-Dist: opentelemetry-api
Requires-Dist: opentelemetry-sdk
Dynamic: license-file
